ipycytoscape/__init__.py
ipycytoscape/_frontend.py
ipycytoscape/_version.py
ipycytoscape/cytoscape.py
ipycytoscape/style.json
ipycytoscape/labextension/package.json
ipycytoscape/labextension/static/106.268f5e0137066962d5de.js
ipycytoscape/labextension/static/142.fd4c373d1e8b92654ea4.js
ipycytoscape/labextension/static/480.8f6d1c7254a91da370a1.js
ipycytoscape/labextension/static/578.09ce99ddc2c07047f895.js
ipycytoscape/labextension/static/58.6846eb7cf4206803b3ab.js
ipycytoscape/labextension/static/58.6846eb7cf4206803b3ab.js.LICENSE.txt
ipycytoscape/labextension/static/69.766fd55b470a4fa78bae.js
ipycytoscape/labextension/static/69.766fd55b470a4fa78bae.js.LICENSE.txt
ipycytoscape/labextension/static/703.293e1b765e744ce5b028.js
ipycytoscape/labextension/static/784.c8d0f5710e5439362104.js
ipycytoscape/labextension/static/878.afc7af901c2338934a68.js
ipycytoscape/labextension/static/981.3153022aa852d392db21.js
ipycytoscape/labextension/static/981.3153022aa852d392db21.js.LICENSE.txt
ipycytoscape/labextension/static/remoteEntry.2598bb44edcc46dad172.js
ipycytoscape/labextension/static/style.js
ipycytoscape/labextension/static/third-party-licenses.json
ipycytoscape/nbextension/__init__.py
ipycytoscape/nbextension/static/extension.js
ipycytoscape/nbextension/static/index.js
ipycytoscape/nbextension/static/index.js.LICENSE.txt
ipycytoscape/nbextension/static/index.js.map
ipycytoscape/tests/__init__.py
ipycytoscape/tests/_util.py
ipycytoscape/tests/conftest.py
ipycytoscape/tests/test_graph_creation.py
ipycytoscape/tests/test_graph_deletion.py
ipycytoscape/tests/test_graph_methods.py
ipycytoscape/tests/test_nbextension_path.py
ipycytoscape-1.3.3.data/data/etc/jupyter/nbconfig/notebook.d/jupyter-cytoscape.json
ipycytoscape-1.3.3.data/data/share/jupyter/labextensions/jupyter-cytoscape/package.json
ipycytoscape-1.3.3.data/data/share/jupyter/labextensions/jupyter-cytoscape/static/106.268f5e0137066962d5de.js
ipycytoscape-1.3.3.dist-info/LICENSE
ipycytoscape-1.3.3.dist-info/METADATA
ipycytoscape-1.3.3.dist-info/WHEEL
ipycytoscape-1.3.3.dist-info/top_level.txt
ipycytoscape-1.3.3.dist-info/RECORD
