Metadata-Version: 2.1
Name: ipycytoscape
Version: 1.3.3
Summary: A Cytoscape widget for Jupyter
Home-page: https://github.com/cytoscape/ipycytoscape
Author: Mariana Meireles
Author-email: mariana.meireles@quantstack.net
License: BSD
Keywords: Jupyter,Widgets,IPython
Platform: Linux
Platform: Mac OS X
Platform: Windows
Classifier: Intended Audience :: Developers
Classifier: Intended Audience :: Science/Research
Classifier: License :: OSI Approved :: BSD License
Classifier: Programming Language :: Python
Classifier: Programming Language :: Python :: 3
Classifier: Programming Language :: Python :: 3.4
Classifier: Programming Language :: Python :: 3.5
Classifier: Programming Language :: Python :: 3.6
Classifier: Programming Language :: Python :: 3.7
Classifier: Programming Language :: Python :: 3.8
Classifier: Programming Language :: Python :: 3.9
Classifier: Framework :: Jupyter
Provides-Extra: test
Provides-Extra: examples
Provides-Extra: docs
Provides-Extra: neo4j
License-File: LICENSE
